.gitignore
Readme.md
div_test.py
setup.py
shared_memory_wrapper/__init__.py
shared_memory_wrapper/file_writing.py
shared_memory_wrapper/object_traversal.py
shared_memory_wrapper/posix_shared_memory.py
shared_memory_wrapper/python_shared_memory.py
shared_memory_wrapper/shared_array_map_reduce.py
shared_memory_wrapper/shared_memory.py
shared_memory_wrapper/shared_memory_v2.py
shared_memory_wrapper/util.py
shared_memory_wrapper.egg-info/PKG-INFO
shared_memory_wrapper.egg-info/SOURCES.txt
shared_memory_wrapper.egg-info/dependency_links.txt
shared_memory_wrapper.egg-info/not-zip-safe
shared_memory_wrapper.egg-info/requires.txt
shared_memory_wrapper.egg-info/top_level.txt
tests/benchmark.py
tests/benchmark2.py
tests/test_dataclass.py
tests/test_map_reduce.py
tests/test_object_traversal.py
tests/test_objects.py
tests/test_private_variables.py
tests/test_python_shared_memory.py
tests/test_remove_shared_memory.py
tests/test_shared_array_map_reduce.py
tests/test_shared_memory.py
tests/test_shared_memory_v2.py
tests/test_util.py