Metadata-Version: 2.1
Name: shared-memory-wrapper
Version: 0.0.31
Summary: Shared Memory Wrapper
Home-page: http://github.com/ivargr/shared_memory_wrapper
Author: Ivar Grytten
Author-email: 
License: MIT
Classifier: Programming Language :: Python :: 3
